Workbook

Sheet Overview
A1: Sales Funnel Analytics
A2: Key metrics computed live from the Data sheet - change a row there and these update.
A4: Total Leads | B4: Win Rate | C4: Revenue Won | D4: Avg Deal Size
A5: =COUNTA(Data!$A$2:$A$7001) | B5: =ROUND(COUNTIF(Data!$I$2:$I$7001,"Won")/A5,3) | C5: =ROUND(SUMIFS(Data!$K$2:$K$7001,Data!$I$2:$I$7001,"Won"),2) | D5: =ROUND(AVERAGEIFS(Data!$K$2:$K$7001,Data!$I$2:$I$7001,"Won"),2)
A7: Top Source by Win Rate | C7: Top Lost Reason by Value | E7: Top Rep by Revenue
A8: =INDEX('Win Rate by Source'!A2:A8,MATCH(MAX('Win Rate by Source'!D2:D8),'Win Rate by Source'!D2:D8,0)) | C8: =INDEX('Lost Value by Reason'!A2:A6,MATCH(MAX('Lost Value by Reason'!C2:C6),'Lost Value by Reason'!C2:C6,0)) | E8: =INDEX('Rep Leaderboard'!A2:A16,MATCH(MAX('Rep Leaderboard'!E2:E16),'Rep Leaderboard'!E2:E16,0))
A10: Top Funnel Drop-off Stage (biggest % lost vs. previous stage)
A11: See the Funnel sheet - stage-by-stage percentages are listed there.

Sheet Data
A1: lead_id | B1: created_at | C1: source | D1: product | E1: region | F1: rep | G1: response_time_hours | H1: stage_reached | I1: status | J1: lost_reason | K1: deal_value | L1: closed_at | M1: stage_num | N1: response_bucket | O1: created_month
A2: LD-300000 | B2: 2025-11-14 14:30:00 | C2: Webinar | D2: Coding for Kids | E2: International | F2: Rep_15 | G2: 0.57 | H2: Closed | I2: Won | K2: 574.72 | L2: 2025-12-15 09:41:11.226466 | M2: =VLOOKUP(H2,'Stage Order'!$A$2:$B$8,2,FALSE) | N2: =IF(G2<=1,"1. Under 1 hour",IF(G2<=24,"2. 1-24 hours",IF(G2<=72,"3. 1-3 days","4. Over 3 days"))) | O2: =TEXT(B2,"YYYY-MM")
A3: LD-300001 | B3: 2026-06-12 16:52:00 | C3: Organic Search | D3: Language Learning | E3: North Region | F3: Rep_01 | G3: 2.72 | H3: Contacted | I3: Open | M3: =VLOOKUP(H3,'Stage Order'!$A$2:$B$8,2,FALSE) | N3: =IF(G3<=1,"1. Under 1 hour",IF(G3<=24,"2. 1-24 hours",IF(G3<=72,"3. 1-3 days","4. Over 3 days"))) | O3: =TEXT(B3,"YYYY-MM")
A4: LD-300002 | B4: 2026-01-21 15:02:00 | C4: Organic Search | D4: Coding for Kids | E4: South Region | F4: Rep_12 | G4: 1.63 | H4: Demo Completed | I4: Lost | J4: Went With Competitor | K4: 673.32 | L4: 2026-02-25 19:23:42.793161 | M4: =VLOOKUP(H4,'Stage Order'!$A$2:$B$8,2,FALSE) | N4: =IF(G4<=1,"1. Under 1 hour",IF(G4<=24,"2. 1-24 hours",IF(G4<=72,"3. 1-3 days","4. Over 3 days"))) | O4: =TEXT(B4,"YYYY-MM")
A5: LD-300003 | B5: 2025-08-28 15:26:00 | C5: Referral | D5: K-12 Math | E5: South Region | F5: Rep_07 | G5: 1.77 | H5: Contacted | I5: Open | M5: =VLOOKUP(H5,'Stage Order'!$A$2:$B$8,2,FALSE) | N5: =IF(G5<=1,"1. Under 1 hour",IF(G5<=24,"2. 1-24 hours",IF(G5<=72,"3. 1-3 days","4. Over 3 days"))) | O5: =TEXT(B5,"YYYY-MM")
A6: LD-300004 | B6: 2026-06-03 10:00:00 | C6: Paid Search | D6: Language Learning | E6: West Region | F6: Rep_13 | G6: 2.73 | H6: Lead | I6: Open | M6: =VLOOKUP(H6,'Stage Order'!$A$2:$B$8,2,FALSE) | N6: =IF(G6<=1,"1. Under 1 hour",IF(G6<=24,"2. 1-24 hours",IF(G6<=72,"3. 1-3 days","4. Over 3 days"))) | O6: =TEXT(B6,"YYYY-MM")
A7: LD-300005 | B7: 2025-09-19 20:36:00 | C7: Organic Search | D7: K-12 Math | E7: International | F7: Rep_15 | G7: 2.29 | H7: Contacted | I7: Open | M7: =VLOOKUP(H7,'Stage Order'!$A$2:$B$8,2,FALSE) | N7: =IF(G7<=1,"1. Under 1 hour",IF(G7<=24,"2. 1-24 hours",IF(G7<=72,"3. 1-3 days","4. Over 3 days"))) | O7: =TEXT(B7,"YYYY-MM")
A8: LD-300006 | B8: 2025-11-14 14:03:00 | C8: Paid Search | D8: K-12 Math | E8: North Region | F8: Rep_06 | G8: 3.21 | H8: Contacted | I8: Open | M8: =VLOOKUP(H8,'Stage Order'!$A$2:$B$8,2,FALSE) | N8: =IF(G8<=1,"1. Under 1 hour",IF(G8<=24,"2. 1-24 hours",IF(G8<=72,"3. 1-3 days","4. Over 3 days"))) | O8: =TEXT(B8,"YYYY-MM")
A9: LD-300007 | B9: 2025-09-01 17:03:00 | C9: Paid Search | D9: K-12 Math | E9: North Region | F9: Rep_01 | G9: 0.48 | H9: Contacted | I9: Open | M9: =VLOOKUP(H9,'Stage Order'!$A$2:$B$8,2,FALSE) | N9: =IF(G9<=1,"1. Under 1 hour",IF(G9<=24,"2. 1-24 hours",IF(G9<=72,"3. 1-3 days","4. Over 3 days"))) | O9: =TEXT(B9,"YYYY-MM")
A10: LD-300008 | B10: 2025-08-25 19:40:00 | C10: Referral | D10: Coding for Kids | E10: South Region | F10: Rep_07 | G10: 2.55 | H10: Closed | I10: Won | K10: 723.67 | L10: 2025-10-16 20:41:44.872095 | M10: =VLOOKUP(H10,'Stage Order'!$A$2:$B$8,2,FALSE) | N10: =IF(G10<=1,"1. Under 1 hour",IF(G10<=24,"2. 1-24 hours",IF(G10<=72,"3. 1-3 days","4. Over 3 days"))) | O10: =TEXT(B10,"YYYY-MM")
A11: LD-300009 | B11: 2026-06-03 14:05:00 | C11: Paid Search | D11: K-12 Math | E11: South Region | F11: Rep_12 | G11: 6.24 | H11: Contacted | I11: Open | M11: =VLOOKUP(H11,'Stage Order'!$A$2:$B$8,2,FALSE) | N11: =IF(G11<=1,"1. Under 1 hour",IF(G11<=24,"2. 1-24 hours",IF(G11<=72,"3. 1-3 days","4. Over 3 days"))) | O11: =TEXT(B11,"YYYY-MM")
A12: LD-300010 | B12: 2026-06-22 11:08:00 | C12: Partner Channel | D12: Competitive Exam Prep | E12: International | F12: Rep_05 | G12: 2.95 | H12: Contacted | I12: Open | M12: =VLOOKUP(H12,'Stage Order'!$A$2:$B$8,2,FALSE) | N12: =IF(G12<=1,"1. Under 1 hour",IF(G12<=24,"2. 1-24 hours",IF(G12<=72,"3. 1-3 days","4. Over 3 days"))) | O12: =TEXT(B12,"YYYY-MM")
A13: LD-300011 | B13: 2025-11-11 15:49:00 | C13: Cold Outreach | D13: Competitive Exam Prep | E13: International | F13: Rep_10 | G13: 1 | H13: Lead | I13: Open | M13: =VLOOKUP(H13,'Stage Order'!$A$2:$B$8,2,FALSE) | N13: =IF(G13<=1,"1. Under 1 hour",IF(G13<=24,"2. 1-24 hours",IF(G13<=72,"3. 1-3 days","4. Over 3 days"))) | O13: =TEXT(B13,"YYYY-MM")
A14: LD-300012 | B14: 2025-03-28 14:32:00 | C14: Webinar | D14: Coding for Kids | E14: West Region | F14: Rep_13 | G14: 3 | H14: Closed | I14: Won | K14: 603.05 | L14: 2025-05-02 11:58:34.056521 | M14: =VLOOKUP(H14,'Stage Order'!$A$2:$B$8,2,FALSE) | N14: =IF(G14<=1,"1. Under 1 hour",IF(G14<=24,"2. 1-24 hours",IF(G14<=72,"3. 1-3 days","4. Over 3 days"))) | O14: =TEXT(B14,"YYYY-MM")
A15: LD-300013 | B15: 2025-03-10 20:45:00 | C15: Referral | D15: Coding for Kids | E15: North Region | F15: Rep_06 | G15: 4.93 | H15: Contacted | I15: Open | M15: =VLOOKUP(H15,'Stage Order'!$A$2:$B$8,2,FALSE) | N15: =IF(G15<=1,"1. Under 1 hour",IF(G15<=24,"2. 1-24 hours",IF(G15<=72,"3. 1-3 days","4. Over 3 days"))) | O15: =TEXT(B15,"YYYY-MM")
A16: LD-300014 | B16: 2026-05-04 17:50:00 | C16: Cold Outreach | D16: Language Learning | E16: East Region | F16: Rep_04 | G16: 2.18 | H16: Lead | I16: Open | M16: =VLOOKUP(H16,'Stage Order'!$A$2:$B$8,2,FALSE) | N16: =IF(G16<=1,"1. Under 1 hour",IF(G16<=24,"2. 1-24 hours",IF(G16<=72,"3. 1-3 days","4. Over 3 days"))) | O16: =TEXT(B16,"YYYY-MM")
A17: LD-300015 | B17: 2025-06-11 07:10:00 | C17: Organic Search | D17: K-12 Math | E17: South Region | F17: Rep_02 | G17: 5.4 | H17: Contacted | I17: Open | M17: =VLOOKUP(H17,'Stage Order'!$A$2:$B$8,2,FALSE) | N17: =IF(G17<=1,"1. Under 1 hour",IF(G17<=24,"2. 1-24 hours",IF(G17<=72,"3. 1-3 days","4. Over 3 days"))) | O17: =TEXT(B17,"YYYY-MM")
A18: LD-300016 | B18: 2025-02-28 09:06:00 | C18: Paid Search | D18: Study Abroad Prep | E18: West Region | F18: Rep_13 | G18: 6.82 | H18: Demo Completed | I18: Lost | J18: No Response / Ghosted | K18: 1379.65 | L18: 2025-03-28 10:20:43.782866 | M18: =VLOOKUP(H18,'Stage Order'!$A$2:$B$8,2,FALSE) | N18: =IF(G18<=1,"1. Under 1 hour",IF(G18<=24,"2. 1-24 hours",IF(G18<=72,"3. 1-3 days","4. Over 3 days"))) | O18: =TEXT(B18,"YYYY-MM")
A19: LD-300017 | B19: 2026-04-04 11:09:00 | C19: Webinar | D19: Competitive Exam Prep | E19: East Region | F19: Rep_04 | G19: 4.1 | H19: Contacted | I19: Open | M19: =VLOOKUP(H19,'Stage Order'!$A$2:$B$8,2,FALSE) | N19: =IF(G19<=1,"1. Under 1 hour",IF(G19<=24,"2. 1-24 hours",IF(G19<=72,"3. 1-3 days","4. Over 3 days"))) | O19: =TEXT(B19,"YYYY-MM")
A20: LD-300018 | B20: 2025-09-29 09:35:00 | C20: Referral | D20: Coding for Kids | E20: North Region | F20: Rep_06 | G20: 5.16 | H20: Contacted | I20: Open | M20: =VLOOKUP(H20,'Stage Order'!$A$2:$B$8,2,FALSE) | N20: =IF(G20<=1,"1. Under 1 hour",IF(G20<=24,"2. 1-24 hours",IF(G20<=72,"3. 1-3 days","4. Over 3 days"))) | O20: =TEXT(B20,"YYYY-MM")
A21: LD-300019 | B21: 2025-07-17 11:05:00 | C21: Cold Outreach | D21: Study Abroad Prep | E21: North Region | F21: Rep_11 | G21: 3.97 | H21: Lead | I21: Open | M21: =VLOOKUP(H21,'Stage Order'!$A$2:$B$8,2,FALSE) | N21: =IF(G21<=1,"1. Under 1 hour",IF(G21<=24,"2. 1-24 hours",IF(G21<=72,"3. 1-3 days","4. Over 3 days"))) | O21: =TEXT(B21,"YYYY-MM")
A22: LD-300020 | B22: 2025-12-27 10:09:00 | C22: Paid Search | D22: K-12 Math | E22: South Region | F22: Rep_07 | G22: 1.97 | H22: Closed | I22: Won | K22: 423.65 | L22: 2026-01-31 19:29:05.287792 | M22: =VLOOKUP(H22,'Stage Order'!$A$2:$B$8,2,FALSE) | N22: =IF(G22<=1,"1. Under 1 hour",IF(G22<=24,"2. 1-24 hours",IF(G22<=72,"3. 1-3 days","4. Over 3 days"))) | O22: =TEXT(B22,"YYYY-MM")
A23: LD-300021 | B23: 2025-07-07 17:46:00 | C23: Paid Search | D23: K-12 Math | E23: East Region | F23: Rep_09 | G23: 3.27 | H23: Demo Completed | I23: Lost | J23: Bad Timing | K23: 491.48 | L23: 2025-07-31 00:34:05.025358 | M23: =VLOOKUP(H23,'Stage Order'!$A$2:$B$8,2,FALSE) | N23: =IF(G23<=1,"1. Under 1 hour",IF(G23<=24,"2. 1-24 hours",IF(G23<=72,"3. 1-3 days","4. Over 3 days"))) | O23: =TEXT(B23,"YYYY-MM")
A24: LD-300022 | B24: 2025-04-09 19:52:00 | C24: Referral | D24: K-12 Math | E24: West Region | F24: Rep_08 | G24: 1.76 | H24: Closed | I24: Won | K24: 443.38 | L24: 2025-05-14 21:34:45.733557 | M24: =VLOOKUP(H24,'Stage Order'!$A$2:$B$8,2,FALSE) | N24: =IF(G24<=1,"1. Under 1 hour",IF(G24<=24,"2. 1-24 hours",IF(G24<=72,"3. 1-3 days","4. Over 3 days"))) | O24: =TEXT(B24,"YYYY-MM")
A25: LD-300023 | B25: 2025-01-30 18:27:00 | C25: Webinar | D25: Study Abroad Prep | E25: International | F25: Rep_10 | G25: 7.24 | H25: Contacted | I25: Open | M25: =VLOOKUP(H25,'Stage Order'!$A$2:$B$8,2,FALSE) | N25: =IF(G25<=1,"1. Under 1 hour",IF(G25<=24,"2. 1-24 hours",IF(G25<=72,"3. 1-3 days","4. Over 3 days"))) | O25: =TEXT(B25,"YYYY-MM")
A26: LD-300024 | B26: 2025-04-18 09:52:00 | C26: Webinar | D26: Language Learning | E26: South Region | F26: Rep_12 | G26: 2.76 | H26: Contacted | I26: Open | M26: =VLOOKUP(H26,'Stage Order'!$A$2:$B$8,2,FALSE) | N26: =IF(G26<=1,"1. Under 1 hour",IF(G26<=24,"2. 1-24 hours",IF(G26<=72,"3. 1-3 days","4. Over 3 days"))) | O26: =TEXT(B26,"YYYY-MM")
A27: LD-300025 | B27: 2025-08-25 14:06:00 | C27: Social Media | D27: Language Learning | E27: South Region | F27: Rep_07 | G27: 6.56 | H27: Lead | I27: Open | M27: =VLOOKUP(H27,'Stage Order'!$A$2:$B$8,2,FALSE) | N27: =IF(G27<=1,"1. Under 1 hour",IF(G27<=24,"2. 1-24 hours",IF(G27<=72,"3. 1-3 days","4. Over 3 days"))) | O27: =TEXT(B27,"YYYY-MM")
A28: LD-300026 | B28: 2025-07-18 12:47:00 | C28: Webinar | D28: Study Abroad Prep | E28: North Region | F28: Rep_01 | G28: 1.39 | H28: Demo Scheduled | I28: Open | M28: =VLOOKUP(H28,'Stage Order'!$A$2:$B$8,2,FALSE) | N28: =IF(G28<=1,"1. Under 1 hour",IF(G28<=24,"2. 1-24 hours",IF(G28<=72,"3. 1-3 days","4. Over 3 days"))) | O28: =TEXT(B28,"YYYY-MM")
A29: LD-300027 | B29: 2025-02-28 08:10:00 | C29: Social Media | D29: Competitive Exam Prep | E29: East Region | F29: Rep_04 | G29: 1.33 | H29: Lead | I29: Open | M29: =VLOOKUP(H29,'Stage Order'!$A$2:$B$8,2,FALSE) | N29: =IF(G29<=1,"1. Under 1 hour",IF(G29<=24,"2. 1-24 hours",IF(G29<=72,"3. 1-3 days","4. Over 3 days"))) | O29: =TEXT(B29,"YYYY-MM")
A30: LD-300028 | B30: 2026-02-13 10:50:00 | C30: Social Media | D30: K-12 Math | E30: South Region | F30: Rep_12 | G30: 1.08 | H30: Demo Scheduled | I30: Open | M30: =VLOOKUP(H30,'Stage Order'!$A$2:$B$8,2,FALSE) | N30: =IF(G30<=1,"1. Under 1 hour",IF(G30<=24,"2. 1-24 hours",IF(G30<=72,"3. 1-3 days","4. Over 3 days"))) | O30: =TEXT(B30,"YYYY-MM")
A31: LD-300029 | B31: 2025-05-16 19:39:00 | C31: Paid Search | D31: K-12 Math | E31: North Region | F31: Rep_01 | G31: 3.12 | H31: Contacted | I31: Open | M31: =VLOOKUP(H31,'Stage Order'!$A$2:$B$8,2,FALSE) | N31: =IF(G31<=1,"1. Under 1 hour",IF(G31<=24,"2. 1-24 hours",IF(G31<=72,"3. 1-3 days","4. Over 3 days"))) | O31: =TEXT(B31,"YYYY-MM")
A32: LD-300030 | B32: 2025-11-27 13:56:00 | C32: Referral | D32: K-12 Math | E32: West Region | F32: Rep_03 | G32: 4.02 | H32: Negotiation | I32: Lost | J32: Price Objection | K32: 447.9 | L32: 2026-01-24 08:30:40.903513 | M32: =VLOOKUP(H32,'Stage Order'!$A$2:$B$8,2,FALSE) | N32: =IF(G32<=1,"1. Under 1 hour",IF(G32<=24,"2. 1-24 hours",IF(G32<=72,"3. 1-3 days","4. Over 3 days"))) | O32: =TEXT(B32,"YYYY-MM")
A33: LD-300031 | B33: 2026-02-06 14:26:00 | C33: Cold Outreach | D33: K-12 Math | E33: South Region | F33: Rep_07 | G33: 22.8 | H33: Contacted | I33: Open | M33: =VLOOKUP(H33,'Stage Order'!$A$2:$B$8,2,FALSE) | N33: =IF(G33<=1,"1. Under 1 hour",IF(G33<=24,"2. 1-24 hours",IF(G33<=72,"3. 1-3 days","4. Over 3 days"))) | O33: =TEXT(B33,"YYYY-MM")
A34: LD-300032 | B34: 2026-04-12 19:06:00 | C34: Webinar | D34: Coding for Kids | E34: East Region | F34: Rep_14 | G34: 8.48 | H34: Proposal Sent | I34: Lost | J34: Price Objection | K34: 549.71 | L34: 2026-05-23 18:53:38.125827 | M34: =VLOOKUP(H34,'Stage Order'!$A$2:$B$8,2,FALSE) | N34: =IF(G34<=1,"1. Under 1 hour",IF(G34<=24,"2. 1-24 hours",IF(G34<=72,"3. 1-3 days","4. Over 3 days"))) | O34: =TEXT(B34,"YYYY-MM")
A35: LD-300033 | B35: 2025-04-03 20:22:00 | C35: Webinar | D35: Competitive Exam Prep | E35: East Region | F35: Rep_09 | G35: 7.92 | H35: Negotiation | I35: Lost | J35: Price Objection | K35: 813.36 | L35: 2025-05-31 22:08:19.446724 | M35: =VLOOKUP(H35,'Stage Order'!$A$2:$B$8,2,FALSE) | N35: =IF(G35<=1,"1. Under 1 hour",IF(G35<=24,"2. 1-24 hours",IF(G35<=72,"3. 1-3 days","4. Over 3 days"))) | O35: =TEXT(B35,"YYYY-MM")
A36: LD-300034 | B36: 2025-12-24 20:45:00 | C36: Paid Search | D36: Language Learning | E36: West Region | F36: Rep_08 | G36: 6.48 | H36: Contacted | I36: Open | M36: =VLOOKUP(H36,'Stage Order'!$A$2:$B$8,2,FALSE) | N36: =IF(G36<=1,"1. Under 1 hour",IF(G36<=24,"2. 1-24 hours",IF(G36<=72,"3. 1-3 days","4. Over 3 days"))) | O36: =TEXT(B36,"YYYY-MM")
A37: LD-300035 | B37: 2025-01-20 20:37:00 | C37: Social Media | D37: Coding for Kids | E37: West Region | F37: Rep_03 | G37: 1.46 | H37: Demo Completed | I37: Lost | J37: No Response / Ghosted | K37: 727.15 | L37: 2025-02-21 23:44:22.327292 | M37: =VLOOKUP(H37,'Stage Order'!$A$2:$B$8,2,FALSE) | N37: =IF(G37<=1,"1. Under 1 hour",IF(G37<=24,"2. 1-24 hours",IF(G37<=72,"3. 1-3 days","4. Over 3 days"))) | O37: =TEXT(B37,"YYYY-MM")
A38: LD-300036 | B38: 2025-03-25 13:49:00 | C38: Webinar | D38: Coding for Kids | E38: West Region | F38: Rep_08 | G38: 1.36 | H38: Negotiation | I38: Lost | J38: No Response / Ghosted | K38: 703.8 | L38: 2025-05-04 10:39:20.298738 | M38: =VLOOKUP(H38,'Stage Order'!$A$2:$B$8,2,FALSE) | N38: =IF(G38<=1,"1. Under 1 hour",IF(G38<=24,"2. 1-24 hours",IF(G38<=72,"3. 1-3 days","4. Over 3 days"))) | O38: =TEXT(B38,"YYYY-MM")
A39: LD-300037 | B39: 2026-05-04 07:42:00 | C39: Cold Outreach | D39: Coding for Kids | E39: West Region | F39: Rep_08 | G39: 1.37 | H39: Lead | I39: Open | M39: =VLOOKUP(H39,'Stage Order'!$A$2:$B$8,2,FALSE) | N39: =IF(G39<=1,"1. Under 1 hour",IF(G39<=24,"2. 1-24 hours",IF(G39<=72,"3. 1-3 days","4. Over 3 days"))) | O39: =TEXT(B39,"YYYY-MM")
A40: LD-300038 | B40: 2025-05-16 15:22:00 | C40: Paid Search | D40: Competitive Exam Prep | E40: South Region | F40: Rep_07 | G40: 1.25 | H40: Contacted | I40: Open | M40: =VLOOKUP(H40,'Stage Order'!$A$2:$B$8,2,FALSE) | N40: =IF(G40<=1,"1. Under 1 hour",IF(G40<=24,"2. 1-24 hours",IF(G40<=72,"3. 1-3 days","4. Over 3 days"))) | O40: =TEXT(B40,"YYYY-MM")
A41: LD-300039 | B41: 2026-02-26 20:16:00 | C41: Paid Search | D41: K-12 Math | E41: East Region | F41: Rep_14 | G41: 18.15 | H41: Lead | I41: Open | M41: =VLOOKUP(H41,'Stage Order'!$A$2:$B$8,2,FALSE) | N41: =IF(G41<=1,"1. Under 1 hour",IF(G41<=24,"2. 1-24 hours",IF(G41<=72,"3. 1-3 days","4. Over 3 days"))) | O41: =TEXT(B41,"YYYY-MM")
A42: LD-300040 | B42: 2025-03-13 08:13:00 | C42: Paid Search | D42: Competitive Exam Prep | E42: North Region | F42: Rep_11 | G42: 5.64 | H42: Contacted | I42: Open | M42: =VLOOKUP(H42,'Stage Order'!$A$2:$B$8,2,FALSE) | N42: =IF(G42<=1,"1. Under 1 hour",IF(G42<=24,"2. 1-24 hours",IF(G42<=72,"3. 1-3 days","4. Over 3 days"))) | O42: =TEXT(B42,"YYYY-MM")
A43: LD-300041 | B43: 2026-03-18 17:40:00 | C43: Paid Search | D43: Coding for Kids | E43: North Region | F43: Rep_06 | G43: 8.36 | H43: Lead | I43: Open | M43: =VLOOKUP(H43,'Stage Order'!$A$2:$B$8,2,FALSE) | N43: =IF(G43<=1,"1. Under 1 hour",IF(G43<=24,"2. 1-24 hours",IF(G43<=72,"3. 1-3 days","4. Over 3 days"))) | O43: =TEXT(B43,"YYYY-MM")
A44: LD-300042 | B44: 2026-03-14 17:30:00 | C44: Webinar | D44: Competitive Exam Prep | E44: North Region | F44: Rep_01 | G44: 1.37 | H44: Closed | I44: Won | K44: 904.9 | L44: 2026-04-30 00:05:39.115725 | M44: =VLOOKUP(H44,'Stage Order'!$A$2:$B$8,2,FALSE) | N44: =IF(G44<=1,"1. Under 1 hour",IF(G44<=24,"2. 1-24 hours",IF(G44<=72,"3. 1-3 days","4. Over 3 days"))) | O44: =TEXT(B44,"YYYY-MM")
A45: LD-300043 | B45: 2025-08-05 07:38:00 | C45: Webinar | D45: Coding for Kids | E45: North Region | F45: Rep_06 | G45: 2.98 | H45: Contacted | I45: Open | M45: =VLOOKUP(H45,'Stage Order'!$A$2:$B$8,2,FALSE) | N45: =IF(G45<=1,"1. Under 1 hour",IF(G45<=24,"2. 1-24 hours",IF(G45<=72,"3. 1-3 days","4. Over 3 days"))) | O45: =TEXT(B45,"YYYY-MM")
A46: LD-300044 | B46: 2026-02-23 19:16:00 | C46: Referral | D46: Language Learning | E46: East Region | F46: Rep_09 | G46: 0.92 | H46: Negotiation | I46: Lost | J46: Price Objection | K46: 311.45 | L46: 2026-03-24 04:39:50.403026 | M46: =VLOOKUP(H46,'Stage Order'!$A$2:$B$8,2,FALSE) | N46: =IF(G46<=1,"1. Under 1 hour",IF(G46<=24,"2. 1-24 hours",IF(G46<=72,"3. 1-3 days","4. Over 3 days"))) | O46: =TEXT(B46,"YYYY-MM")
A47: LD-300045 | B47: 2026-06-05 13:50:00 | C47: Organic Search | D47: K-12 Math | E47: East Region | F47: Rep_04 | G47: 5.34 | H47: Contacted | I47: Open | M47: =VLOOKUP(H47,'Stage Order'!$A$2:$B$8,2,FALSE) | N47: =IF(G47<=1,"1. Under 1 hour",IF(G47<=24,"2. 1-24 hours",IF(G47<=72,"3. 1-3 days","4. Over 3 days"))) | O47: =TEXT(B47,"YYYY-MM")
A48: LD-300046 | B48: 2025-09-14 18:40:00 | C48: Cold Outreach | D48: Coding for Kids | E48: North Region | F48: Rep_01 | G48: 3.62 | H48: Lead | I48: Open | M48: =VLOOKUP(H48,'Stage Order'!$A$2:$B$8,2,FALSE) | N48: =IF(G48<=1,"1. Under 1 hour",IF(G48<=24,"2. 1-24 hours",IF(G48<=72,"3. 1-3 days","4. Over 3 days"))) | O48: =TEXT(B48,"YYYY-MM")
A49: LD-300047 | B49: 2025-07-15 17:56:00 | C49: Partner Channel | D49: Study Abroad Prep | E49: North Region | F49: Rep_01 | G49: 7.02 | H49: Contacted | I49: Open | M49: =VLOOKUP(H49,'Stage Order'!$A$2:$B$8,2,FALSE) | N49: =IF(G49<=1,"1. Under 1 hour",IF(G49<=24,"2. 1-24 hours",IF(G49<=72,"3. 1-3 days","4. Over 3 days"))) | O49: =TEXT(B49,"YYYY-MM")
A50: LD-300048 | B50: 2026-05-27 20:22:00 | C50: Referral | D50: Coding for Kids | E50: West Region | F50: Rep_08 | G50: 3.41 | H50: Closed | I50: Won | K50: 572.7 | L50: 2026-06-29 01:06:46.159443 | M50: =VLOOKUP(H50,'Stage Order'!$A$2:$B$8,2,FALSE) | N50: =IF(G50<=1,"1. Under 1 hour",IF(G50<=24,"2. 1-24 hours",IF(G50<=72,"3. 1-3 days","4. Over 3 days"))) | O50: =TEXT(B50,"YYYY-MM")
A51: LD-300049 | B51: 2025-05-28 11:58:00 | C51: Partner Channel | D51: K-12 Math | E51: East Region | F51: Rep_09 | G51: 1.27 | H51: Demo Completed | I51: Lost | J51: No Response / Ghosted | K51: 459.38 | L51: 2025-06-21 00:50:06.965092 | M51: =VLOOKUP(H51,'Stage Order'!$A$2:$B$8,2,FALSE) | N51: =IF(G51<=1,"1. Under 1 hour",IF(G51<=24,"2. 1-24 hours",IF(G51<=72,"3. 1-3 days","4. Over 3 days"))) | O51: =TEXT(B51,"YYYY-MM")
A52: LD-300050 | B52: 2026-02-18 20:45:00 | C52: Referral | D52: K-12 Math | E52: East Region | F52: Rep_04 | G52: 0.27 | H52: Closed | I52: Won | K52: 464.24 | L52: 2026-04-01 16:27:38.559368 | M52: =VLOOKUP(H52,'Stage Order'!$A$2:$B$8,2,FALSE) | N52: =IF(G52<=1,"1. Under 1 hour",IF(G52<=24,"2. 1-24 hours",IF(G52<=72,"3. 1-3 days","4. Over 3 days"))) | O52: =TEXT(B52,"YYYY-MM")
A53: LD-300051 | B53: 2026-01-27 17:56:00 | C53: Webinar | D53: Competitive Exam Prep | E53: West Region | F53: Rep_08 | G53: 1.12 | H53: Contacted | I53: Open | M53: =VLOOKUP(H53,'Stage Order'!$A$2:$B$8,2,FALSE) | N53: =IF(G53<=1,"1. Under 1 hour",IF(G53<=24,"2. 1-24 hours",IF(G53<=72,"3. 1-3 days","4. Over 3 days"))) | O53: =TEXT(B53,"YYYY-MM")
A54: LD-300052 | B54: 2025-11-02 16:13:00 | C54: Paid Search | D54: Competitive Exam Prep | E54: East Region | F54: Rep_04 | G54: 8.27 | H54: Negotiation | I54: Lost | J54: Price Objection | K54: 1000.06 | L54: 2025-12-11 05:57:50.501004 | M54: =VLOOKUP(H54,'Stage Order'!$A$2:$B$8,2,FALSE) | N54: =IF(G54<=1,"1. Under 1 hour",IF(G54<=24,"2. 1-24 hours",IF(G54<=72,"3. 1-3 days","4. Over 3 days"))) | O54: =TEXT(B54,"YYYY-MM")
A55: LD-300053 | B55: 2025-10-14 08:23:00 | C55: Cold Outreach | D55: Competitive Exam Prep | E55: East Region | F55: Rep_04 | G55: 2.19 | H55: Lead | I55: Open | M55: =VLOOKUP(H55,'Stage Order'!$A$2:$B$8,2,FALSE) | N55: =IF(G55<=1,"1. Under 1 hour",IF(G55<=24,"2. 1-24 hours",IF(G55<=72,"3. 1-3 days","4. Over 3 days"))) | O55: =TEXT(B55,"YYYY-MM")
A56: LD-300054 | B56: 2025-09-02 19:57:00 | C56: Organic Search | D56: Coding for Kids | E56: South Region | F56: Rep_12 | G56: 2.6 | H56: Contacted | I56: Open | M56: =VLOOKUP(H56,'Stage Order'!$A$2:$B$8,2,FALSE) | N56: =IF(G56<=1,"1. Under 1 hour",IF(G56<=24,"2. 1-24 hours",IF(G56<=72,"3. 1-3 days","4. Over 3 days"))) | O56: =TEXT(B56,"YYYY-MM")
A57: LD-300055 | B57: 2025-08-22 13:58:00 | C57: Partner Channel | D57: Competitive Exam Prep | E57: North Region | F57: Rep_06 | G57: 2.89 | H57: Contacted | I57: Open | M57: =VLOOKUP(H57,'Stage Order'!$A$2:$B$8,2,FALSE) | N57: =IF(G57<=1,"1. Under 1 hour",IF(G57<=24,"2. 1-24 hours",IF(G57<=72,"3. 1-3 days","4. Over 3 days"))) | O57: =TEXT(B57,"YYYY-MM")
A58: LD-300056 | B58: 2025-05-08 20:34:00 | C58: Referral | D58: Competitive Exam Prep | E58: West Region | F58: Rep_08 | G58: 2.61 | H58: Closed | I58: Won | K58: 960.65 | L58: 2025-06-16 17:50:27.592409 | M58: =VLOOKUP(H58,'Stage Order'!$A$2:$B$8,2,FALSE) | N58: =IF(G58<=1,"1. Under 1 hour",IF(G58<=24,"2. 1-24 hours",IF(G58<=72,"3. 1-3 days","4. Over 3 days"))) | O58: =TEXT(B58,"YYYY-MM")
A59: LD-300057 | B59: 2025-08-13 10:46:00 | C59: Social Media | D59: Coding for Kids | E59: West Region | F59: Rep_08 | G59: 15.1 | H59: Demo Completed | I59: Lost | J59: Price Objection | K59: 574.74 | L59: 2025-09-16 07:25:05.485357 | M59: =VLOOKUP(H59,'Stage Order'!$A$2:$B$8,2,FALSE) | N59: =IF(G59<=1,"1. Under 1 hour",IF(G59<=24,"2. 1-24 hours",IF(G59<=72,"3. 1-3 days","4. Over 3 days"))) | O59: =TEXT(B59,"YYYY-MM")
A60: LD-300058 | B60: 2025-09-26 13:29:00 | C60: Organic Search | D60: K-12 Math | E60: South Region | F60: Rep_12 | G60: 2.14 | H60: Demo Scheduled | I60: Open | M60: =VLOOKUP(H60,'Stage Order'!$A$2:$B$8,2,FALSE) | N60: =IF(G60<=1,"1. Under 1 hour",IF(G60<=24,"2. 1-24 hours",IF(G60<=72,"3. 1-3 days","4. Over 3 days"))) | O60: =TEXT(B60,"YYYY-MM")
A61: LD-300059 | B61: 2026-02-20 17:48:00 | C61: Webinar | D61: Competitive Exam Prep | E61: East Region | F61: Rep_04 | G61: 3.49 | H61: Contacted | I61: Open | M61: =VLOOKUP(H61,'Stage Order'!$A$2:$B$8,2,FALSE) | N61: =IF(G61<=1,"1. Under 1 hour",IF(G61<=24,"2. 1-24 hours",IF(G61<=72,"3. 1-3 days","4. Over 3 days"))) | O61: =TEXT(B61,"YYYY-MM")
A62: LD-300060 | B62: 2025-11-26 16:14:00 | C62: Organic Search | D62: K-12 Math | E62: South Region | F62: Rep_07 | G62: 1.72 | H62: Proposal Sent | I62: Lost | J62: Price Objection | K62: 552.96 | L62: 2025-12-22 02:45:06.304175 | M62: =VLOOKUP(H62,'Stage Order'!$A$2:$B$8,2,FALSE) | N62: =IF(G62<=1,"1. Under 1 hour",IF(G62<=24,"2. 1-24 hours",IF(G62<=72,"3. 1-3 days","4. Over 3 days"))) | O62: =TEXT(B62,"YYYY-MM")
A63: LD-300061 | B63: 2026-04-17 12:12:00 | C63: Cold Outreach | D63: Competitive Exam Prep | E63: West Region | F63: Rep_13 | G63: 2.8 | H63: Contacted | I63: Open | M63: =VLOOKUP(H63,'Stage Order'!$A$2:$B$8,2,FALSE) | N63: =IF(G63<=1,"1. Under 1 hour",IF(G63<=24,"2. 1-24 hours",IF(G63<=72,"3. 1-3 days","4. Over 3 days"))) | O63: =TEXT(B63,"YYYY-MM")
A64: LD-300062 | B64: 2026-03-10 20:40:00 | C64: Referral | D64: Competitive Exam Prep | E64: North Region | F64: Rep_01 | G64: 12.16 | H64: Contacted | I64: Open | M64: =VLOOKUP(H64,'Stage Order'!$A$2:$B$8,2,FALSE) | N64: =IF(G64<=1,"1. Under 1 hour",IF(G64<=24,"2. 1-24 hours",IF(G64<=72,"3. 1-3 days","4. Over 3 days"))) | O64: =TEXT(B64,"YYYY-MM")
A65: LD-300063 | B65: 2026-06-19 08:42:00 | C65: Paid Search | D65: Study Abroad Prep | E65: North Region | F65: Rep_01 | G65: 5.18 | H65: Contacted | I65: Open | M65: =VLOOKUP(H65,'Stage Order'!$A$2:$B$8,2,FALSE) | N65: =IF(G65<=1,"1. Under 1 hour",IF(G65<=24,"2. 1-24 hours",IF(G65<=72,"3. 1-3 days","4. Over 3 days"))) | O65: =TEXT(B65,"YYYY-MM")
A66: LD-300064 | B66: 2026-05-19 13:50:00 | C66: Webinar | D66: Coding for Kids | E66: International | F66: Rep_10 | G66: 2.27 | H66: Contacted | I66: Open | M66: =VLOOKUP(H66,'Stage Order'!$A$2:$B$8,2,FALSE) | N66: =IF(G66<=1,"1. Under 1 hour",IF(G66<=24,"2. 1-24 hours",IF(G66<=72,"3. 1-3 days","4. Over 3 days"))) | O66: =TEXT(B66,"YYYY-MM")
A67: LD-300065 | B67: 2026-01-19 19:04:00 | C67: Paid Search | D67: Competitive Exam Prep | E67: International | F67: Rep_15 | G67: 1.32 | H67: Contacted | I67: Open | M67: =VLOOKUP(H67,'Stage Order'!$A$2:$B$8,2,FALSE) | N67: =IF(G67<=1,"1. Under 1 hour",IF(G67<=24,"2. 1-24 hours",IF(G67<=72,"3. 1-3 days","4. Over 3 days"))) | O67: =TEXT(B67,"YYYY-MM")
A68: LD-300066 | B68: 2026-02-12 12:13:00 | C68: Social Media | D68: Competitive Exam Prep | E68: South Region | F68: Rep_12 | G68: 4.01 | H68: Contacted | I68: Open | M68: =VLOOKUP(H68,'Stage Order'!$A$2:$B$8,2,FALSE) | N68: =IF(G68<=1,"1. Under 1 hour",IF(G68<=24,"2. 1-24 hours",IF(G68<=72,"3. 1-3 days","4. Over 3 days"))) | O68: =TEXT(B68,"YYYY-MM")
A69: LD-300067 | B69: 2025-01-24 14:28:00 | C69: Webinar | D69: K-12 Math | E69: North Region | F69: Rep_11 | G69: 2.48 | H69: Closed | I69: Won | K69: 485.63 | L69: 2025-02-24 23:37:36.990452 | M69: =VLOOKUP(H69,'Stage Order'!$A$2:$B$8,2,FALSE) | N69: =IF(G69<=1,"1. Under 1 hour",IF(G69<=24,"2. 1-24 hours",IF(G69<=72,"3. 1-3 days","4. Over 3 days"))) | O69: =TEXT(B69,"YYYY-MM")
A70: LD-300068 | B70: 2026-05-15 15:56:00 | C70: Paid Search | D70: Coding for Kids | E70: West Region | F70: Rep_03 | G70: 2.03 | H70: Contacted | I70: Open | M70: =VLOOKUP(H70,'Stage Order'!$A$2:$B$8,2,FALSE) | N70: =IF(G70<=1,"1. Under 1 hour",IF(G70<=24,"2. 1-24 hours",IF(G70<=72,"3. 1-3 days","4. Over 3 days"))) | O70: =TEXT(B70,"YYYY-MM")
A71: LD-300069 | B71: 2025-06-19 09:43:00 | C71: Organic Search | D71: Study Abroad Prep | E71: South Region | F71: Rep_02 | G71: 0.44 | H71: Lead | I71: Open | M71: =VLOOKUP(H71,'Stage Order'!$A$2:$B$8,2,FALSE) | N71: =IF(G71<=1,"1. Under 1 hour",IF(G71<=24,"2. 1-24 hours",IF(G71<=72,"3. 1-3 days","4. Over 3 days"))) | O71: =TEXT(B71,"YYYY-MM")
A72: LD-300070 | B72: 2025-09-18 20:47:00 | C72: Social Media | D72: Coding for Kids | E72: West Region | F72: Rep_03 | G72: 6.31 | H72: Negotiation | I72: Lost | J72: Price Objection | K72: 529.34 | L72: 2025-10-28 04:15:35.442355 | M72: =VLOOKUP(H72,'Stage Order'!$A$2:$B$8,2,FALSE) | N72: =IF(G72<=1,"1. Under 1 hour",IF(G72<=24,"2. 1-24 hours",IF(G72<=72,"3. 1-3 days","4. Over 3 days"))) | O72: =TEXT(B72,"YYYY-MM")
A73: LD-300071 | B73: 2025-11-21 10:23:00 | C73: Cold Outreach | D73: Coding for Kids | E73: North Region | F73: Rep_11 | G73: 8.56 | H73: Demo Scheduled | I73: Open | M73: =VLOOKUP(H73,'Stage Order'!$A$2:$B$8,2,FALSE) | N73: =IF(G73<=1,"1. Under 1 hour",IF(G73<=24,"2. 1-24 hours",IF(G73<=72,"3. 1-3 days","4. Over 3 days"))) | O73: =TEXT(B73,"YYYY-MM")
A74: LD-300072 | B74: 2025-04-22 08:15:00 | C74: Cold Outreach | D74: Competitive Exam Prep | E74: South Region | F74: Rep_02 | G74: 19.31 | H74: Lead | I74: Open | M74: =VLOOKUP(H74,'Stage Order'!$A$2:$B$8,2,FALSE) | N74: =IF(G74<=1,"1. Under 1 hour",IF(G74<=24,"2. 1-24 hours",IF(G74<=72,"3. 1-3 days","4. Over 3 days"))) | O74: =TEXT(B74,"YYYY-MM")
A75: LD-300073 | B75: 2025-10-11 16:06:00 | C75: Organic Search | D75: K-12 Math | E75: West Region | F75: Rep_08 | G75: 5.22 | H75: Closed | I75: Won | K75: 414.78 | L75: 2025-11-13 01:28:41.921589 | M75: =VLOOKUP(H75,'Stage Order'!$A$2:$B$8,2,FALSE) | N75: =IF(G75<=1,"1. Under 1 hour",IF(G75<=24,"2. 1-24 hours",IF(G75<=72,"3. 1-3 days","4. Over 3 days"))) | O75: =TEXT(B75,"YYYY-MM")
A76: LD-300074 | B76: 2025-05-02 18:19:00 | C76: Cold Outreach | D76: Competitive Exam Prep | E76: South Region | F76: Rep_12 | G76: 3.25 | H76: Demo Completed | I76: Lost | J76: Went With Competitor | K76: 1164.37 | L76: 2025-06-04 05:01:54.067642 | M76: =VLOOKUP(H76,'Stage Order'!$A$2:$B$8,2,FALSE) | N76: =IF(G76<=1,"1. Under 1 hour",IF(G76<=24,"2. 1-24 hours",IF(G76<=72,"3. 1-3 days","4. Over 3 days"))) | O76: =TEXT(B76,"YYYY-MM")
A77: LD-300075 | B77: 2025-08-28 14:07:00 | C77: Organic Search | D77: Study Abroad Prep | E77: West Region | F77: Rep_03 | G77: 5.77 | H77: Contacted | I77: Open | M77: =VLOOKUP(H77,'Stage Order'!$A$2:$B$8,2,FALSE) | N77: =IF(G77<=1,"1. Under 1 hour",IF(G77<=24,"2. 1-24 hours",IF(G77<=72,"3. 1-3 days","4. Over 3 days"))) | O77: =TEXT(B77,"YYYY-MM")
A78: LD-300076 | B78: 2026-05-18 20:21:00 | C78: Organic Search | D78: K-12 Math | E78: South Region | F78: Rep_12 | G78: 8.49 | H78: Contacted | I78: Open | M78: =VLOOKUP(H78,'Stage Order'!$A$2:$B$8,2,FALSE) | N78: =IF(G78<=1,"1. Under 1 hour",IF(G78<=24,"2. 1-24 hours",IF(G78<=72,"3. 1-3 days","4. Over 3 days"))) | O78: =TEXT(B78,"YYYY-MM")
A79: LD-300077 | B79: 2025-03-06 09:24:00 | C79: Organic Search | D79: Coding for Kids | E79: North Region | F79: Rep_11 | G79: 6.65 | H79: Lead | I79: Open | M79: =VLOOKUP(H79,'Stage Order'!$A$2:$B$8,2,FALSE) | N79: =IF(G79<=1,"1. Under 1 hour",IF(G79<=24,"2. 1-24 hours",IF(G79<=72,"3. 1-3 days","4. Over 3 days"))) | O79: =TEXT(B79,"YYYY-MM")
A80: LD-300078 | B80: 2025-08-06 14:15:00 | C80: Social Media | D80: Coding for Kids | E80: North Region | F80: Rep_01 | G80: 2.92 | H80: Contacted | I80: Open | M80: =VLOOKUP(H80,'Stage Order'!$A$2:$B$8,2,FALSE) | N80: =IF(G80<=1,"1. Under 1 hour",IF(G80<=24,"2. 1-24 hours",IF(G80<=72,"3. 1-3 days","4. Over 3 days"))) | O80: =TEXT(B80,"YYYY-MM")
A81: LD-300079 | B81: 2026-04-26 14:59:00 | C81: Organic Search | D81: Study Abroad Prep | E81: International | F81: Rep_05 | G81: 9.22 | H81: Proposal Sent | I81: Lost | J81: Price Objection | K81: 1493.43 | L81: 2026-06-19 09:03:14.537196 | M81: =VLOOKUP(H81,'Stage Order'!$A$2:$B$8,2,FALSE) | N81: =IF(G81<=1,"1. Under 1 hour",IF(G81<=24,"2. 1-24 hours",IF(G81<=72,"3. 1-3 days","4. Over 3 days"))) | O81: =TEXT(B81,"YYYY-MM")
A82: LD-300080 | B82: 2025-09-26 12:56:00 | C82: Paid Search | D82: Coding for Kids | E82: North Region | F82: Rep_06 | G82: 5.8 | H82: Lead | I82: Open | M82: =VLOOKUP(H82,'Stage Order'!$A$2:$B$8,2,FALSE) | N82: =IF(G82<=1,"1. Under 1 hour",IF(G82<=24,"2. 1-24 hours",IF(G82<=72,"3. 1-3 days","4. Over 3 days"))) | O82: =TEXT(B82,"YYYY-MM")
A83: LD-300081 | B83: 2025-08-27 20:08:00 | C83: Webinar | D83: K-12 Math | E83: International | F83: Rep_15 | G83: 1.32 | H83: Contacted | I83: Open | M83: =VLOOKUP(H83,'Stage Order'!$A$2:$B$8,2,FALSE) | N83: =IF(G83<=1,"1. Under 1 hour",IF(G83<=24,"2. 1-24 hours",IF(G83<=72,"3. 1-3 days","4. Over 3 days"))) | O83: =TEXT(B83,"YYYY-MM")
A84: LD-300082 | B84: 2025-07-24 14:36:00 | C84: Social Media | D84: Competitive Exam Prep | E84: North Region | F84: Rep_01 | G84: 2.76 | H84: Lead | I84: Open | M84: =VLOOKUP(H84,'Stage Order'!$A$2:$B$8,2,FALSE) | N84: =IF(G84<=1,"1. Under 1 hour",IF(G84<=24,"2. 1-24 hours",IF(G84<=72,"3. 1-3 days","4. Over 3 days"))) | O84: =TEXT(B84,"YYYY-MM")
A85: LD-300083 | B85: 2026-05-08 19:43:00 | C85: Organic Search | D85: K-12 Math | E85: North Region | F85: Rep_01 | G85: 1.34 | H85: Proposal Sent | I85: Lost | J85: Price Objection | K85: 467.4 | L85: 2026-06-12 00:03:20.076902 | M85: =VLOOKUP(H85,'Stage Order'!$A$2:$B$8,2,FALSE) | N85: =IF(G85<=1,"1. Under 1 hour",IF(G85<=24,"2. 1-24 hours",IF(G85<=72,"3. 1-3 days","4. Over 3 days"))) | O85: =TEXT(B85,"YYYY-MM")
A86: LD-300084 | B86: 2025-12-04 19:27:00 | C86: Social Media | D86: Language Learning | E86: West Region | F86: Rep_08 | G86: 0.52 | H86: Closed | I86: Won | K86: 303.78 | L86: 2026-01-05 05:54:32.836208 | M86: =VLOOKUP(H86,'Stage Order'!$A$2:$B$8,2,FALSE) | N86: =IF(G86<=1,"1. Under 1 hour",IF(G86<=24,"2. 1-24 hours",IF(G86<=72,"3. 1-3 days","4. Over 3 days"))) | O86: =TEXT(B86,"YYYY-MM")
A87: LD-300085 | B87: 2026-03-18 18:31:00 | C87: Social Media | D87: K-12 Math | E87: West Region | F87: Rep_13 | G87: 2.82 | H87: Contacted | I87: Open | M87: =VLOOKUP(H87,'Stage Order'!$A$2:$B$8,2,FALSE) | N87: =IF(G87<=1,"1. Under 1 hour",IF(G87<=24,"2. 1-24 hours",IF(G87<=72,"3. 1-3 days","4. Over 3 days"))) | O87: =TEXT(B87,"YYYY-MM")
A88: LD-300086 | B88: 2026-03-20 14:44:00 | C88: Social Media | D88: Language Learning | E88: West Region | F88: Rep_03 | G88: 2.96 | H88: Lead | I88: Open | M88: =VLOOKUP(H88,'Stage Order'!$A$2:$B$8,2,FALSE) | N88: =IF(G88<=1,"1. Under 1 hour",IF(G88<=24,"2. 1-24 hours",IF(G88<=72,"3. 1-3 days","4. Over 3 days"))) | O88: =TEXT(B88,"YYYY-MM")
A89: LD-300087 | B89: 2025-10-09 17:46:00 | C89: Paid Search | D89: Language Learning | E89: North Region | F89: Rep_06 | G89: 2.58 | H89: Lead | I89: Open | M89: =VLOOKUP(H89,'Stage Order'!$A$2:$B$8,2,FALSE) | N89: =IF(G89<=1,"1. Under 1 hour",IF(G89<=24,"2. 1-24 hours",IF(G89<=72,"3. 1-3 days","4. Over 3 days"))) | O89: =TEXT(B89,"YYYY-MM")
A90: LD-300088 | B90: 2026-06-26 14:23:00 | C90: Social Media | D90: Competitive Exam Prep | E90: South Region | F90: Rep_12 | G90: 2.02 | H90: Contacted | I90: Open | M90: =VLOOKUP(H90,'Stage Order'!$A$2:$B$8,2,FALSE) | N90: =IF(G90<=1,"1. Under 1 hour",IF(G90<=24,"2. 1-24 hours",IF(G90<=72,"3. 1-3 days","4. Over 3 days"))) | O90: =TEXT(B90,"YYYY-MM")
A91: LD-300089 | B91: 2025-12-04 20:54:00 | C91: Organic Search | D91: Study Abroad Prep | E91: West Region | F91: Rep_13 | G91: 1.59 | H91: Contacted | I91: Open | M91: =VLOOKUP(H91,'Stage Order'!$A$2:$B$8,2,FALSE) | N91: =IF(G91<=1,"1. Under 1 hour",IF(G91<=24,"2. 1-24 hours",IF(G91<=72,"3. 1-3 days","4. Over 3 days"))) | O91: =TEXT(B91,"YYYY-MM")
A92: LD-300090 | B92: 2026-02-23 09:31:00 | C92: Paid Search | D92: Coding for Kids | E92: East Region | F92: Rep_09 | G92: 8.89 | H92: Demo Scheduled | I92: Open | M92: =VLOOKUP(H92,'Stage Order'!$A$2:$B$8,2,FALSE) | N92: =IF(G92<=1,"1. Under 1 hour",IF(G92<=24,"2. 1-24 hours",IF(G92<=72,"3. 1-3 days","4. Over 3 days"))) | O92: =TEXT(B92,"YYYY-MM")
A93: LD-300091 | B93: 2025-08-07 08:26:00 | C93: Referral | D93: Competitive Exam Prep | E93: East Region | F93: Rep_14 | G93: 4.16 | H93: Negotiation | I93: Lost | J93: Price Objection | K93: 1181.29 | L93: 2025-09-16 10:00:49.420102 | M93: =VLOOKUP(H93,'Stage Order'!$A$2:$B$8,2,FALSE) | N93: =IF(G93<=1,"1. Under 1 hour",IF(G93<=24,"2. 1-24 hours",IF(G93<=72,"3. 1-3 days","4. Over 3 days"))) | O93: =TEXT(B93,"YYYY-MM")
A94: LD-300092 | B94: 2025-01-17 13:02:00 | C94: Cold Outreach | D94: Coding for Kids | E94: East Region | F94: Rep_14 | G94: 2.7 | H94: Lead | I94: Open | M94: =VLOOKUP(H94,'Stage Order'!$A$2:$B$8,2,FALSE) | N94: =IF(G94<=1,"1. Under 1 hour",IF(G94<=24,"2. 1-24 hours",IF(G94<=72,"3. 1-3 days","4. Over 3 days"))) | O94: =TEXT(B94,"YYYY-MM")
A95: LD-300093 | B95: 2025-09-05 07:05:00 | C95: Organic Search | D95: K-12 Math | E95: South Region | F95: Rep_12 | G95: 0.99 | H95: Closed | I95: Won | K95: 496.76 | L95: 2025-10-16 12:05:33.132715 | M95: =VLOOKUP(H95,'Stage Order'!$A$2:$B$8,2,FALSE) | N95: =IF(G95<=1,"1. Under 1 hour",IF(G95<=24,"2. 1-24 hours",IF(G95<=72,"3. 1-3 days","4. Over 3 days"))) | O95: =TEXT(B95,"YYYY-MM")
A96: LD-300094 | B96: 2025-08-14 19:49:00 | C96: Organic Search | D96: Competitive Exam Prep | E96: South Region | F96: Rep_07 | G96: 1.57 | H96: Proposal Sent | I96: Lost | J96: Bad Timing | K96: 914.85 | L96: 2025-10-07 02:50:04.365043 | M96: =VLOOKUP(H96,'Stage Order'!$A$2:$B$8,2,FALSE) | N96: =IF(G96<=1,"1. Under 1 hour",IF(G96<=24,"2. 1-24 hours",IF(G96<=72,"3. 1-3 days","4. Over 3 days"))) | O96: =TEXT(B96,"YYYY-MM")
A97: LD-300095 | B97: 2025-02-04 08:16:00 | C97: Paid Search | D97: Language Learning | E97: West Region | F97: Rep_13 | G97: 3.37 | H97: Demo Scheduled | I97: Open | M97: =VLOOKUP(H97,'Stage Order'!$A$2:$B$8,2,FALSE) | N97: =IF(G97<=1,"1. Under 1 hour",IF(G97<=24,"2. 1-24 hours",IF(G97<=72,"3. 1-3 days","4. Over 3 days"))) | O97: =TEXT(B97,"YYYY-MM")
A98: LD-300096 | B98: 2025-06-05 11:09:00 | C98: Cold Outreach | D98: Competitive Exam Prep | E98: North Region | F98: Rep_01 | G98: 0.79 | H98: Contacted | I98: Open | M98: =VLOOKUP(H98,'Stage Order'!$A$2:$B$8,2,FALSE) | N98: =IF(G98<=1,"1. Under 1 hour",IF(G98<=24,"2. 1-24 hours",IF(G98<=72,"3. 1-3 days","4. Over 3 days"))) | O98: =TEXT(B98,"YYYY-MM")
A99: LD-300097 | B99: 2025-11-26 19:33:00 | C99: Organic Search | D99: Competitive Exam Prep | E99: South Region | F99: Rep_12 | G99: 1.27 | H99: Contacted | I99: Open | M99: =VLOOKUP(H99,'Stage Order'!$A$2:$B$8,2,FALSE) | N99: =IF(G99<=1,"1. Under 1 hour",IF(G99<=24,"2. 1-24 hours",IF(G99<=72,"3. 1-3 days","4. Over 3 days"))) | O99: =TEXT(B99,"YYYY-MM")
A100: LD-300098 | B100: 2025-04-03 12:49:00 | C100: Social Media | D100: Competitive Exam Prep | E100: International | F100: Rep_05 | G100: 0.61 | H100: Contacted | I100: Open | M100: =VLOOKUP(H100,'Stage Order'!$A$2:$B$8,2,FALSE) | N100: =IF(G100<=1,"1. Under 1 hour",IF(G100<=24,"2. 1-24 hours",IF(G100<=72,"3. 1-3 days","4. Over 3 days"))) | O100: =TEXT(B100,"YYYY-MM")
...

Sheet Stage Order
A1: stage_name | B1: stage_num
A2: Lead | B2: 1
A3: Contacted | B3: 2
A4: Demo Scheduled | B4: 3
A5: Demo Completed | B5: 4
A6: Proposal Sent | B6: 5
A7: Negotiation | B7: 6
A8: Closed | B8: 7

Sheet Funnel
A1: stage | B1: stage_num | C1: leads_reaching_or_beyond | D1: pct_of_total
A2: Lead | B2: 1 | C2: =COUNTIF(Data!$M$2:$M$7001,">="&B2) | D2: =ROUND(C2/COUNTA(Data!$A$2:$A$7001)*100,1)
A3: Contacted | B3: 2 | C3: =COUNTIF(Data!$M$2:$M$7001,">="&B3) | D3: =ROUND(C3/COUNTA(Data!$A$2:$A$7001)*100,1)
A4: Demo Scheduled | B4: 3 | C4: =COUNTIF(Data!$M$2:$M$7001,">="&B4) | D4: =ROUND(C4/COUNTA(Data!$A$2:$A$7001)*100,1)
A5: Demo Completed | B5: 4 | C5: =COUNTIF(Data!$M$2:$M$7001,">="&B5) | D5: =ROUND(C5/COUNTA(Data!$A$2:$A$7001)*100,1)
A6: Proposal Sent | B6: 5 | C6: =COUNTIF(Data!$M$2:$M$7001,">="&B6) | D6: =ROUND(C6/COUNTA(Data!$A$2:$A$7001)*100,1)
A7: Negotiation | B7: 6 | C7: =COUNTIF(Data!$M$2:$M$7001,">="&B7) | D7: =ROUND(C7/COUNTA(Data!$A$2:$A$7001)*100,1)
A8: Closed | B8: 7 | C8: =COUNTIF(Data!$M$2:$M$7001,">="&B8) | D8: =ROUND(C8/COUNTA(Data!$A$2:$A$7001)*100,1)

Sheet Win Rate by Source
A1: source | B1: total_leads | C1: won | D1: win_rate_pct
A2: Cold Outreach | B2: =COUNTIF(Data!$C$2:$C$7001,A2) | C2: =COUNTIFS(Data!$C$2:$C$7001,A2,Data!$I$2:$I$7001,"Won") | D2: =ROUND(C2/B2*100,1)
A3: Organic Search | B3: =COUNTIF(Data!$C$2:$C$7001,A3) | C3: =COUNTIFS(Data!$C$2:$C$7001,A3,Data!$I$2:$I$7001,"Won") | D3: =ROUND(C3/B3*100,1)
A4: Paid Search | B4: =COUNTIF(Data!$C$2:$C$7001,A4) | C4: =COUNTIFS(Data!$C$2:$C$7001,A4,Data!$I$2:$I$7001,"Won") | D4: =ROUND(C4/B4*100,1)
A5: Partner Channel | B5: =COUNTIF(Data!$C$2:$C$7001,A5) | C5: =COUNTIFS(Data!$C$2:$C$7001,A5,Data!$I$2:$I$7001,"Won") | D5: =ROUND(C5/B5*100,1)
A6: Referral | B6: =COUNTIF(Data!$C$2:$C$7001,A6) | C6: =COUNTIFS(Data!$C$2:$C$7001,A6,Data!$I$2:$I$7001,"Won") | D6: =ROUND(C6/B6*100,1)
A7: Social Media | B7: =COUNTIF(Data!$C$2:$C$7001,A7) | C7: =COUNTIFS(Data!$C$2:$C$7001,A7,Data!$I$2:$I$7001,"Won") | D7: =ROUND(C7/B7*100,1)
A8: Webinar | B8: =COUNTIF(Data!$C$2:$C$7001,A8) | C8: =COUNTIFS(Data!$C$2:$C$7001,A8,Data!$I$2:$I$7001,"Won") | D8: =ROUND(C8/B8*100,1)

Sheet Speed to Lead
A1: response_bucket | B1: total_leads | C1: won | D1: win_rate_pct
A2: 1. Under 1 hour | B2: =COUNTIF(Data!$N$2:$N$7001,A2) | C2: =COUNTIFS(Data!$N$2:$N$7001,A2,Data!$I$2:$I$7001,"Won") | D2: =ROUND(C2/B2*100,1)
A3: 2. 1-24 hours | B3: =COUNTIF(Data!$N$2:$N$7001,A3) | C3: =COUNTIFS(Data!$N$2:$N$7001,A3,Data!$I$2:$I$7001,"Won") | D3: =ROUND(C3/B3*100,1)
A4: 3. 1-3 days | B4: =COUNTIF(Data!$N$2:$N$7001,A4) | C4: =COUNTIFS(Data!$N$2:$N$7001,A4,Data!$I$2:$I$7001,"Won") | D4: =ROUND(C4/B4*100,1)
A5: 4. Over 3 days | B5: =COUNTIF(Data!$N$2:$N$7001,A5) | C5: =COUNTIFS(Data!$N$2:$N$7001,A5,Data!$I$2:$I$7001,"Won") | D5: =ROUND(C5/B5*100,1)

Sheet Lost Value by Reason
A1: lost_reason | B1: lost_deals | C1: total_lost_value | D1: avg_lost_value
A2: Bad Timing | B2: =COUNTIFS(Data!$I$2:$I$7001,"Lost",Data!$J$2:$J$7001,A2) | C2: =ROUND(SUMIFS(Data!$K$2:$K$7001,Data!$I$2:$I$7001,"Lost",Data!$J$2:$J$7001,A2),2) | D2: =ROUND(AVERAGEIFS(Data!$K$2:$K$7001,Data!$I$2:$I$7001,"Lost",Data!$J$2:$J$7001,A2),2)
A3: Budget Not Approved | B3: =COUNTIFS(Data!$I$2:$I$7001,"Lost",Data!$J$2:$J$7001,A3) | C3: =ROUND(SUMIFS(Data!$K$2:$K$7001,Data!$I$2:$I$7001,"Lost",Data!$J$2:$J$7001,A3),2) | D3: =ROUND(AVERAGEIFS(Data!$K$2:$K$7001,Data!$I$2:$I$7001,"Lost",Data!$J$2:$J$7001,A3),2)
A4: No Response / Ghosted | B4: =COUNTIFS(Data!$I$2:$I$7001,"Lost",Data!$J$2:$J$7001,A4) | C4: =ROUND(SUMIFS(Data!$K$2:$K$7001,Data!$I$2:$I$7001,"Lost",Data!$J$2:$J$7001,A4),2) | D4: =ROUND(AVERAGEIFS(Data!$K$2:$K$7001,Data!$I$2:$I$7001,"Lost",Data!$J$2:$J$7001,A4),2)
A5: Price Objection | B5: =COUNTIFS(Data!$I$2:$I$7001,"Lost",Data!$J$2:$J$7001,A5) | C5: =ROUND(SUMIFS(Data!$K$2:$K$7001,Data!$I$2:$I$7001,"Lost",Data!$J$2:$J$7001,A5),2) | D5: =ROUND(AVERAGEIFS(Data!$K$2:$K$7001,Data!$I$2:$I$7001,"Lost",Data!$J$2:$J$7001,A5),2)
A6: Went With Competitor | B6: =COUNTIFS(Data!$I$2:$I$7001,"Lost",Data!$J$2:$J$7001,A6) | C6: =ROUND(SUMIFS(Data!$K$2:$K$7001,Data!$I$2:$I$7001,"Lost",Data!$J$2:$J$7001,A6),2) | D6: =ROUND(AVERAGEIFS(Data!$K$2:$K$7001,Data!$I$2:$I$7001,"Lost",Data!$J$2:$J$7001,A6),2)

Sheet Rep Leaderboard
A1: rep | B1: total_leads | C1: won | D1: win_rate_pct | E1: total_revenue
A2: Rep_01 | B2: =COUNTIF(Data!$F$2:$F$7001,A2) | C2: =COUNTIFS(Data!$F$2:$F$7001,A2,Data!$I$2:$I$7001,"Won") | D2: =ROUND(C2/B2*100,1) | E2: =ROUND(SUMIFS(Data!$K$2:$K$7001,Data!$F$2:$F$7001,A2,Data!$I$2:$I$7001,"Won"),2)
A3: Rep_02 | B3: =COUNTIF(Data!$F$2:$F$7001,A3) | C3: =COUNTIFS(Data!$F$2:$F$7001,A3,Data!$I$2:$I$7001,"Won") | D3: =ROUND(C3/B3*100,1) | E3: =ROUND(SUMIFS(Data!$K$2:$K$7001,Data!$F$2:$F$7001,A3,Data!$I$2:$I$7001,"Won"),2)
A4: Rep_03 | B4: =COUNTIF(Data!$F$2:$F$7001,A4) | C4: =COUNTIFS(Data!$F$2:$F$7001,A4,Data!$I$2:$I$7001,"Won") | D4: =ROUND(C4/B4*100,1) | E4: =ROUND(SUMIFS(Data!$K$2:$K$7001,Data!$F$2:$F$7001,A4,Data!$I$2:$I$7001,"Won"),2)
A5: Rep_04 | B5: =COUNTIF(Data!$F$2:$F$7001,A5) | C5: =COUNTIFS(Data!$F$2:$F$7001,A5,Data!$I$2:$I$7001,"Won") | D5: =ROUND(C5/B5*100,1) | E5: =ROUND(SUMIFS(Data!$K$2:$K$7001,Data!$F$2:$F$7001,A5,Data!$I$2:$I$7001,"Won"),2)
A6: Rep_05 | B6: =COUNTIF(Data!$F$2:$F$7001,A6) | C6: =COUNTIFS(Data!$F$2:$F$7001,A6,Data!$I$2:$I$7001,"Won") | D6: =ROUND(C6/B6*100,1) | E6: =ROUND(SUMIFS(Data!$K$2:$K$7001,Data!$F$2:$F$7001,A6,Data!$I$2:$I$7001,"Won"),2)
A7: Rep_06 | B7: =COUNTIF(Data!$F$2:$F$7001,A7) | C7: =COUNTIFS(Data!$F$2:$F$7001,A7,Data!$I$2:$I$7001,"Won") | D7: =ROUND(C7/B7*100,1) | E7: =ROUND(SUMIFS(Data!$K$2:$K$7001,Data!$F$2:$F$7001,A7,Data!$I$2:$I$7001,"Won"),2)
A8: Rep_07 | B8: =COUNTIF(Data!$F$2:$F$7001,A8) | C8: =COUNTIFS(Data!$F$2:$F$7001,A8,Data!$I$2:$I$7001,"Won") | D8: =ROUND(C8/B8*100,1) | E8: =ROUND(SUMIFS(Data!$K$2:$K$7001,Data!$F$2:$F$7001,A8,Data!$I$2:$I$7001,"Won"),2)
A9: Rep_08 | B9: =COUNTIF(Data!$F$2:$F$7001,A9) | C9: =COUNTIFS(Data!$F$2:$F$7001,A9,Data!$I$2:$I$7001,"Won") | D9: =ROUND(C9/B9*100,1) | E9: =ROUND(SUMIFS(Data!$K$2:$K$7001,Data!$F$2:$F$7001,A9,Data!$I$2:$I$7001,"Won"),2)
A10: Rep_09 | B10: =COUNTIF(Data!$F$2:$F$7001,A10) | C10: =COUNTIFS(Data!$F$2:$F$7001,A10,Data!$I$2:$I$7001,"Won") | D10: =ROUND(C10/B10*100,1) | E10: =ROUND(SUMIFS(Data!$K$2:$K$7001,Data!$F$2:$F$7001,A10,Data!$I$2:$I$7001,"Won"),2)
A11: Rep_10 | B11: =COUNTIF(Data!$F$2:$F$7001,A11) | C11: =COUNTIFS(Data!$F$2:$F$7001,A11,Data!$I$2:$I$7001,"Won") | D11: =ROUND(C11/B11*100,1) | E11: =ROUND(SUMIFS(Data!$K$2:$K$7001,Data!$F$2:$F$7001,A11,Data!$I$2:$I$7001,"Won"),2)
A12: Rep_11 | B12: =COUNTIF(Data!$F$2:$F$7001,A12) | C12: =COUNTIFS(Data!$F$2:$F$7001,A12,Data!$I$2:$I$7001,"Won") | D12: =ROUND(C12/B12*100,1) | E12: =ROUND(SUMIFS(Data!$K$2:$K$7001,Data!$F$2:$F$7001,A12,Data!$I$2:$I$7001,"Won"),2)
A13: Rep_12 | B13: =COUNTIF(Data!$F$2:$F$7001,A13) | C13: =COUNTIFS(Data!$F$2:$F$7001,A13,Data!$I$2:$I$7001,"Won") | D13: =ROUND(C13/B13*100,1) | E13: =ROUND(SUMIFS(Data!$K$2:$K$7001,Data!$F$2:$F$7001,A13,Data!$I$2:$I$7001,"Won"),2)
... A16: Rep_15 | B16: =COUNTIF(Data!$F$2:$F$7001,A16) | C16: =COUNTIFS(Data!$F$2:$F$7001,A16,Data!$I$2:$I$7001,"Won") | D16: =ROUND(C16/B16*100,1) | E16: =ROUND(SUMIFS(Data!$K$2:$K$7001,Data!$F$2:$F$7001,A16,Data!$I$2:$I$7001,"Won"),2)

Sheet Monthly Trend
A1: month | B1: leads | C1: win_rate_pct
A2: 2025-01 | B2: =COUNTIF(Data!$O$2:$O$7001,A2) | C2: =ROUND(COUNTIFS(Data!$O$2:$O$7001,A2,Data!$I$2:$I$7001,"Won")/B2*100,1)
A3: 2025-02 | B3: =COUNTIF(Data!$O$2:$O$7001,A3) | C3: =ROUND(COUNTIFS(Data!$O$2:$O$7001,A3,Data!$I$2:$I$7001,"Won")/B3*100,1)
A4: 2025-03 | B4: =COUNTIF(Data!$O$2:$O$7001,A4) | C4: =ROUND(COUNTIFS(Data!$O$2:$O$7001,A4,Data!$I$2:$I$7001,"Won")/B4*100,1)
A5: 2025-04 | B5: =COUNTIF(Data!$O$2:$O$7001,A5) | C5: =ROUND(COUNTIFS(Data!$O$2:$O$7001,A5,Data!$I$2:$I$7001,"Won")/B5*100,1)
A6: 2025-05 | B6: =COUNTIF(Data!$O$2:$O$7001,A6) | C6: =ROUND(COUNTIFS(Data!$O$2:$O$7001,A6,Data!$I$2:$I$7001,"Won")/B6*100,1)
A7: 2025-06 | B7: =COUNTIF(Data!$O$2:$O$7001,A7) | C7: =ROUND(COUNTIFS(Data!$O$2:$O$7001,A7,Data!$I$2:$I$7001,"Won")/B7*100,1)
A8: 2025-07 | B8: =COUNTIF(Data!$O$2:$O$7001,A8) | C8: =ROUND(COUNTIFS(Data!$O$2:$O$7001,A8,Data!$I$2:$I$7001,"Won")/B8*100,1)
A9: 2025-08 | B9: =COUNTIF(Data!$O$2:$O$7001,A9) | C9: =ROUND(COUNTIFS(Data!$O$2:$O$7001,A9,Data!$I$2:$I$7001,"Won")/B9*100,1)
A10: 2025-09 | B10: =COUNTIF(Data!$O$2:$O$7001,A10) | C10: =ROUND(COUNTIFS(Data!$O$2:$O$7001,A10,Data!$I$2:$I$7001,"Won")/B10*100,1)
A11: 2025-10 | B11: =COUNTIF(Data!$O$2:$O$7001,A11) | C11: =ROUND(COUNTIFS(Data!$O$2:$O$7001,A11,Data!$I$2:$I$7001,"Won")/B11*100,1)
A12: 2025-11 | B12: =COUNTIF(Data!$O$2:$O$7001,A12) | C12: =ROUND(COUNTIFS(Data!$O$2:$O$7001,A12,Data!$I$2:$I$7001,"Won")/B12*100,1)
A13: 2025-12 | B13: =COUNTIF(Data!$O$2:$O$7001,A13) | C13: =ROUND(COUNTIFS(Data!$O$2:$O$7001,A13,Data!$I$2:$I$7001,"Won")/B13*100,1)
... A19: 2026-06 | B19: =COUNTIF(Data!$O$2:$O$7001,A19) | C19: =ROUND(COUNTIFS(Data!$O$2:$O$7001,A19,Data!$I$2:$I$7001,"Won")/B19*100,1)
